codemcp/__init__.py
codemcp/__main__.py
codemcp/access.py
codemcp/agno.py
codemcp/async_file_utils.py
codemcp/code_command.py
codemcp/common.py
codemcp/config.py
codemcp/file_utils.py
codemcp/git.py
codemcp/git_commit.py
codemcp/git_message.py
codemcp/git_parse_message.py
codemcp/git_query.py
codemcp/glob_pattern.py
codemcp/line_endings.py
codemcp/main.py
codemcp/mcp.py
codemcp/rules.py
codemcp/shell.py
codemcp/testing.py
codemcp/tools/__init__.py
codemcp/tools/chmod.py
codemcp/tools/commit_utils.py
codemcp/tools/edit_file.py
codemcp/tools/git_blame.py
codemcp/tools/git_diff.py
codemcp/tools/git_log.py
codemcp/tools/git_show.py
codemcp/tools/glob.py
codemcp/tools/grep.py
codemcp/tools/init_project.py
codemcp/tools/ls.py
codemcp/tools/mv.py
codemcp/tools/read_file.py
codemcp/tools/rm.py
codemcp/tools/run_command.py
codemcp/tools/think.py
codemcp/tools/write_file.py
mseep_codemcp-0.7.1.dist-info/licenses/LICENSE.txt
mseep_codemcp-0.7.1.dist-info/METADATA
mseep_codemcp-0.7.1.dist-info/WHEEL
mseep_codemcp-0.7.1.dist-info/top_level.txt
mseep_codemcp-0.7.1.dist-info/RECORD
