Metadata-Version: 2.4
Name: mseep-codemcp
Version: 0.7.1
Summary: MCP server for file operations
Home-page: 
Author: mseep
Author-email: support@skydeck.ai
Maintainer: mseep
Maintainer-email: support@skydeck.ai
Keywords: mseep
Classifier: Programming Language :: Python :: 3
Classifier: License :: OSI Approved :: MIT License
Classifier: Operating System :: OS Independent
Requires-Python: >=3.6
License-File: LICENSE.txt
Requires-Dist: mcp[cli]>=1.2.0
Requires-Dist: ruff>=0.9.10
Requires-Dist: toml>=0.10.2
Requires-Dist: tomli>=2.1.1
Requires-Dist: anyio>=3.7.0
Requires-Dist: pyyaml>=6.0.0
Requires-Dist: editorconfig>=0.17.0
Requires-Dist: click>=8.1.8
Requires-Dist: agno>=1.2.16
Requires-Dist: anthropic>=0.49.0
Requires-Dist: fastapi>=0.115.12
Requires-Dist: uvicorn>=0.28.0
Requires-Dist: starlette>=0.35.1
Requires-Dist: google-genai>=1.10.0
Requires-Dist: pathspec>=0.12.1
Dynamic: author
Dynamic: author-email
Dynamic: classifier
Dynamic: description
Dynamic: description-content-type
Dynamic: keywords
Dynamic: license-file
Dynamic: maintainer
Dynamic: maintainer-email
Dynamic: requires-dist
Dynamic: requires-python
Dynamic: summary
